servicex_codegen/__init__.py
servicex_codegen/code_generator.py
servicex_codegen/post_operation.py
servicex_code_gen_lib-1.3.dist-info/LICENSE
servicex_code_gen_lib-1.3.dist-info/WHEEL
servicex_code_gen_lib-1.3.dist-info/METADATA
servicex_code_gen_lib-1.3.dist-info/RECORD
