Metadata-Version: 2.1
Name: servicex-code-gen-lib
Version: 1.3
Summary: Library for creating ServiceX Code Generators
Author: Ben Galewsky
Author-email: bengal1@illinois.edu
Requires-Python: >=3.10,<4.0
Classifier: Programming Language :: Python :: 3
Classifier: Programming Language :: Python :: 3.10
Classifier: Programming Language :: Python :: 3.11
Requires-Dist: Flask (>=2.3.3,<3.0.0)
Requires-Dist: Flask-RESTful (>=0.3.9,<0.4.0)
Requires-Dist: Flask-WTF (>=1.0.1,<2.0.0)
Requires-Dist: Jinja2 (>=3.1.2,<4.0.0)
Requires-Dist: Werkzeug (>=3.0.4,<4.0.0)
Requires-Dist: itsdangerous (>=2.1.2,<3.0.0)
Requires-Dist: requests-toolbelt (>=1.0.0,<2.0.0)
Requires-Dist: urllib3 (>=2.5.0,<3.0.0)
